setup.py
ae_prob_19/Binomialdistribution.py
ae_prob_19/Gaussiandistribution.py
ae_prob_19/Generaldistribution.py
ae_prob_19/__init__.py
ae_prob_19.egg-info/PKG-INFO
ae_prob_19.egg-info/SOURCES.txt
ae_prob_19.egg-info/dependency_links.txt
ae_prob_19.egg-info/not-zip-safe
ae_prob_19.egg-info/top_level.txt